bitfinex_maker_kit/__init__.py
bitfinex_maker_kit/__main__.py
bitfinex_maker_kit/bitfinex_client.py
bitfinex_maker_kit/cli/__init__.py
bitfinex_maker_kit/cli/argument_parser.py
bitfinex_maker_kit/cli/command_router.py
bitfinex_maker_kit/commands/__init__.py
bitfinex_maker_kit/commands/cancel.py
bitfinex_maker_kit/commands/fill_spread.py
bitfinex_maker_kit/commands/list.py
bitfinex_maker_kit/commands/market_make.py
bitfinex_maker_kit/commands/monitor.py
bitfinex_maker_kit/commands/monitor_display.py
bitfinex_maker_kit/commands/monitor_websocket.py
bitfinex_maker_kit/commands/put.py
bitfinex_maker_kit/commands/test.py
bitfinex_maker_kit/commands/update.py
bitfinex_maker_kit/commands/wallet.py
bitfinex_maker_kit/commands/core/__init__.py
bitfinex_maker_kit/commands/core/base_command.py
bitfinex_maker_kit/commands/core/batch_executor.py
bitfinex_maker_kit/commands/core/cancel_order_command.py
bitfinex_maker_kit/commands/core/command_executor.py
bitfinex_maker_kit/commands/core/command_result.py
bitfinex_maker_kit/commands/core/market_make_command.py
bitfinex_maker_kit/commands/core/place_order_command.py
bitfinex_maker_kit/config/__init__.py
bitfinex_maker_kit/config/environment.py
bitfinex_maker_kit/config/trading_config.py
bitfinex_maker_kit/core/__init__.py
bitfinex_maker_kit/core/api_client.py
bitfinex_maker_kit/core/order_fetcher.py
bitfinex_maker_kit/core/order_manager.py
bitfinex_maker_kit/core/order_update_service.py
bitfinex_maker_kit/core/order_validator.py
bitfinex_maker_kit/core/trading_facade.py
bitfinex_maker_kit/domain/__init__.py
bitfinex_maker_kit/domain/amount.py
bitfinex_maker_kit/domain/order_id.py
bitfinex_maker_kit/domain/price.py
bitfinex_maker_kit/domain/symbol.py
bitfinex_maker_kit/services/__init__.py
bitfinex_maker_kit/services/async_trading_service.py
bitfinex_maker_kit/services/batch_request_service.py
bitfinex_maker_kit/services/cache_service.py
bitfinex_maker_kit/services/container.py
bitfinex_maker_kit/services/market_data_service.py
bitfinex_maker_kit-4.7.0.dist-info/licenses/LICENSE
bitfinex_maker_kit-4.7.0.dist-info/METADATA
bitfinex_maker_kit-4.7.0.dist-info/WHEEL
bitfinex_maker_kit-4.7.0.dist-info/entry_points.txt
bitfinex_maker_kit-4.7.0.dist-info/top_level.txt
bitfinex_maker_kit-4.7.0.dist-info/RECORD
