Metadata-Version: 2.4
Name: bitfinex-maker-kit
Version: 4.7.0
Summary: Professional market making toolkit for Bitfinex cryptocurrency exchange
Author: Bitfinex Maker-Kit Contributors
License: MIT
Keywords: bitfinex,cryptocurrency,trading,market-making,automated-trading
Requires-Python: >=3.12
License-File: LICENSE
Requires-Dist: bitfinex-api-py>=3.0.0
Requires-Dist: python-dotenv>=1.0.0
Requires-Dist: asyncio>=3.4.3
Requires-Dist: aiohttp>=3.8.0
Requires-Dist: click>=8.0.0
Requires-Dist: psutil>=5.9.0
Provides-Extra: dev
Requires-Dist: ruff>=0.6.0; extra == "dev"
Requires-Dist: mypy>=1.5.0; extra == "dev"
Requires-Dist: types-psutil; extra == "dev"
Requires-Dist: pytest>=7.4.0; extra == "dev"
Requires-Dist: pytest-cov>=4.1.0; extra == "dev"
Requires-Dist: bandit>=1.7.5; extra == "dev"
Requires-Dist: hypothesis>=6.0.0; extra == "dev"
Requires-Dist: pytest-asyncio>=0.21.0; extra == "dev"
Requires-Dist: pytest-benchmark>=4.0.0; extra == "dev"
Dynamic: license-file
